{
  "logs": [
    {
      "type": "error",
      "data": "Database Connection Failed!",
      "relTime": 4534
    },
    {
      "type": "error",
      "data": "Database Connection Failed!",
      "relTime": 6050
    }
  ],
  "network": [],
  "url": "http://localhost:5173/",
  "ua": "Mozilla/5.0 (Macintosh; Intel Mac OS X 10_15_7) AppleWebKit/537.36 (KHTML, like Gecko) Chrome/143.0.0.0 Safari/537.36",
  "userDescription": "Test",
  "triage": {
    "summary": "Test",
    "reproSteps": [
      "1. User opened the application.",
      "2. User performed interactions.",
      "3. Technical logs were recorded."
    ],
    "severity": "High",
    "reason": "Fallback logic: Error detection triggered based on console logs."
  }
}